{
  "hash": "b14d71ea",
  "configHash": "3563e089",
  "lockfileHash": "8d846096",
  "browserHash": "fbf99288",
  "optimized": {
    "@vueuse/core": {
      "src": "../../../../node_modules/@vueuse/core/index.mjs",
      "file": "@vueuse_core.js",
      "fileHash": "ded70bb5",
      "needsInterop": false
    },
    "@vue/devtools-api": {
      "src": "../../../../node_modules/@vue/devtools-api/lib/esm/index.js",
      "file": "@vue_devtools-api.js",
      "fileHash": "2e482526",
      "needsInterop": false
    },
    "@vuepress/shared": {
      "src": "../../../../node_modules/@vuepress/shared/dist/index.js",
      "file": "@vuepress_shared.js",
      "fileHash": "f60dccd9",
      "needsInterop": false
    },
    "vue": {
      "src": "../../../../node_modules/vue/dist/vue.runtime.esm-bundler.js",
      "file": "vue.js",
      "fileHash": "a5b84b0a",
      "needsInterop": false
    },
    "vue-router": {
      "src": "../../../../node_modules/vue-router/dist/vue-router.esm-bundler.js",
      "file": "vue-router.js",
      "fileHash": "4d6065d9",
      "needsInterop": false
    }
  },
  "chunks": {
    "chunk-UKCZNIRO": {
      "file": "chunk-UKCZNIRO.js"
    },
    "chunk-RY5ODQAQ": {
      "file": "chunk-RY5ODQAQ.js"
    }
  }
}